horsemeat/__init__.py
horsemeat/configwrapper.py
horsemeat/pg.py
horsemeat/version.py
horsemeat/model/__init__.py
horsemeat/model/newsmessage.py
horsemeat/model/session.py
horsemeat/model/user.py
horsemeat/scripts/make-frippery-project
horsemeat/tests/__init__.py
horsemeat/tests/test_configwrapper.py
horsemeat/webapp/__init__.py
horsemeat/webapp/bogusrequest.py
horsemeat/webapp/dispatcher.py
horsemeat/webapp/frameworkhandlers.py
horsemeat/webapp/handler.py
horsemeat/webapp/request.py
horsemeat/webapp/response.py
horsemeat/webapp/scrubber.py
horsemeat/webapp/framework_templates/__init__.py
horsemeat-2.21.7.data/scripts/make-frippery-project
horsemeat-2.21.7.dist-info/DESCRIPTION.rst
horsemeat-2.21.7.dist-info/METADATA
horsemeat-2.21.7.dist-info/RECORD
horsemeat-2.21.7.dist-info/WHEEL
horsemeat-2.21.7.dist-info/metadata.json
horsemeat-2.21.7.dist-info/top_level.txt
