Metadata-Version: 2.0
Name: horsemeat
Version: 2.21.7
Summary: Web framework for the damned.  The mad.
Home-page: https://GitHub.com/216software/horsemeat
Author: 216 Software, LLC
Author-email: info@216software.com
License: UNKNOWN
Platform: UNKNOWN
Classifier: Programming Language :: Python :: 3
Requires-Dist: Jinja2 (>=2.6)
Requires-Dist: PyYAML (>=3.10)
Requires-Dist: Werkzeug (>=0.10.1)
Requires-Dist: clepy (>=0.3.23)
Requires-Dist: decorator (>=3.4.0)
Requires-Dist: gunicorn
Requires-Dist: nose (>=1.3.3)
Requires-Dist: psycopg2 (>=2.7)
